MANIFEST.in
README.md
setup.cfg
setup.py
django_simplemde.egg-info/PKG-INFO
django_simplemde.egg-info/SOURCES.txt
django_simplemde.egg-info/dependency_links.txt
django_simplemde.egg-info/not-zip-safe
django_simplemde.egg-info/requires.txt
django_simplemde.egg-info/top_level.txt
simplemde/__init__.py
simplemde/fields.py
simplemde/utils.py
simplemde/widgets.py
simplemde/__pycache__/__init__.cpython-36.pyc
simplemde/__pycache__/fields.cpython-36.pyc
simplemde/__pycache__/utils.cpython-36.pyc
simplemde/__pycache__/widgets.cpython-36.pyc
simplemde/static/simplemde/simplemde.init.js
simplemde/static/simplemde/simplemde.min.css
simplemde/static/simplemde/simplemde.min.js