Metadata-Version: 1.1
Name: django-simplemde
Version: 0.1.3
Summary: django-simplemde is a WYSIWYG markdown editor for Django
Home-page: https://github.com/onepill/django-simplemde
Author: Siyuan Zhang
Author-email: onepill@gmail.com
License: MIT
Keywords: django,admin,wysiwyg,markdown,editor,simplemde
Platform: UNKNOWN
Classifier: Development Status :: 5 - Production/Stable
Classifier: Environment :: Web Environment
Classifier: Framework :: Django
Classifier: Intended Audience :: Developers
Classifier: License :: OSI Approved :: BSD License
Classifier: Operating System :: OS Independent
Classifier: Programming Language :: Python
